datafusion/__init__.py
datafusion/_internal.abi3.so
datafusion/catalog.py
datafusion/col.py
datafusion/common.py
datafusion/context.py
datafusion/dataframe.py
datafusion/dataframe_formatter.py
datafusion/expr.py
datafusion/functions.py
datafusion/html_formatter.py
datafusion/input/__init__.py
datafusion/input/base.py
datafusion/input/location.py
datafusion/io.py
datafusion/object_store.py
datafusion/plan.py
datafusion/py.typed
datafusion/record_batch.py
datafusion/substrait.py
datafusion/udf.py
datafusion/unparser.py
datafusion/user_defined.py
pathsdata-48.0.3.dist-info/METADATA
pathsdata-48.0.3.dist-info/WHEEL
pathsdata/__init__.py
pathsdata/catalog.py
pathsdata/context.py
pathsdata-48.0.3.dist-info/RECORD
