Metadata-Version: 2.4
Name: pathsdata
Version: 48.0.3
Classifier: Development Status :: 2 - Pre-Alpha
Classifier: Intended Audience :: Developers
Classifier: Operating System :: MacOS
Classifier: Operating System :: Microsoft :: Windows
Classifier: Operating System :: POSIX :: Linux
Classifier: Programming Language :: Python :: 3
Classifier: Programming Language :: Python :: 3.9
Classifier: Programming Language :: Python :: 3.10
Classifier: Programming Language :: Python :: 3.11
Classifier: Programming Language :: Python :: 3.12
Classifier: Programming Language :: Python :: 3.13
Classifier: Programming Language :: Python
Classifier: Programming Language :: Rust
Requires-Dist: pyarrow>=11.0.0
Requires-Dist: typing-extensions ; python_full_version < '3.13'
Summary: Build and run queries against data
Keywords: datafusion,dataframe,rust,query-engine
Home-Page: https://github.com/pathsdata/pathsdata
Requires-Python: >=3.9
Project-URL: homepage, https://github.com/pathsdata/pathsdata
Project-URL: documentation, https://github.com/pathsdata/pathsdata
Project-URL: repository, https://github.com/pathsdata/pathsdata
